pysungrow/__init__.py
pysungrow/__main__.py
pysungrow/client.py
pysungrow/compat.py
pysungrow/definitions/__init__.py
pysungrow/definitions/device.py
pysungrow/definitions/devices/__init__.py
pysungrow/definitions/devices/hybrid.py
pysungrow/definitions/devices/string.py
pysungrow/definitions/variable.py
pysungrow/definitions/variables/__init__.py
pysungrow/definitions/variables/device.py
pysungrow/definitions/variables/general.py
pysungrow/definitions/variables/hybrid.py
pysungrow/definitions/variables/string.py
pysungrow/identify.py
pysungrow/lib/__init__.py
pysungrow/lib/decode.py
pysungrow/lib/encode.py
pysungrow/lib/flag.py
pysungrow/lib/group_variables_by_proximity.py
pysungrow/lib/read_variables.py
pysungrow/lib/write_variable.py
pysungrow/py.typed
pysungrow-1.1.0.dist-info/METADATA
pysungrow-1.1.0.dist-info/WHEEL
pysungrow-1.1.0.dist-info/LICENSE.md
pysungrow-1.1.0.dist-info/RECORD
