Metadata-Version: 2.1
Name: pysungrow
Version: 1.1.0
Summary: Read and manipulate Sungrow inverters
Home-page: https://github.com/02JanDal/pysungrow
License: MIT
Author: Jan Dalheimer
Author-email: jan@dalheimer.de
Requires-Python: >=3.9,<4.0
Classifier: Development Status :: 5 - Production/Stable
Classifier: Framework :: AsyncIO
Classifier: Intended Audience :: Developers
Classifier: License :: OSI Approved :: MIT License
Classifier: Programming Language :: Python :: 3
Classifier: Programming Language :: Python :: 3.9
Classifier: Programming Language :: Python :: 3.10
Classifier: Programming Language :: Python :: 3.11
Classifier: Programming Language :: Python :: 3
Classifier: Programming Language :: Python :: 3.10
Classifier: Programming Language :: Python :: 3.9
Classifier: Topic :: Software Development :: Libraries :: Python Modules
Classifier: Topic :: System :: Networking
Requires-Dist: pymodbus (>=2.5.3)
Project-URL: Repository, https://github.com/02JanDal/pysungrow
